Caly/__init__.py
Caly-1.0.data/data/conf/sounds/invalid_keypress.mp3
Caly-1.0.data/data/conf/sounds/pop.wav
Caly-1.0.data/data/conf/sounds/tock.wav
Caly-1.0.data/data/conf/txt/words_00.txt
Caly-1.0.data/data/conf/txt/words_01.txt
Caly-1.0.data/data/conf/txt/words_02.txt
Caly-1.0.data/data/conf/txt/words_03.txt
Caly-1.0.data/scripts/caly
Caly-1.0.dist-info/DESCRIPTION.rst
Caly-1.0.dist-info/METADATA
Caly-1.0.dist-info/RECORD
Caly-1.0.dist-info/WHEEL
Caly-1.0.dist-info/metadata.json
Caly-1.0.dist-info/top_level.txt
