Metadata-Version: 2.0
Name: Caly
Version: 1.0
Summary: caly module
Home-page: http://obswww.unige.ch/~revaz
Author: Yves Revaz
Author-email: yves.revaz@epfl.ch
License: GPLv3
Platform: UNKNOWN
Requires-Dist: numpy
Requires-Dist: pyQt5
